terminal_stonks/__init__.py
terminal_stonks/k_chart.py
terminal_stonks-0.1.0.dist-info/licenses/LICENSE
terminal_stonks-0.1.0.dist-info/METADATA
terminal_stonks-0.1.0.dist-info/WHEEL
terminal_stonks-0.1.0.dist-info/top_level.txt
terminal_stonks-0.1.0.dist-info/RECORD
