Metadata-Version: 2.4
Name: terminal-stonks
Version: 0.1.0
Summary: Terminal-based stock chart visualization library
Author-email: Sun Jiaxuan <sunjiaxuan@hotmail.com>
Maintainer-email: Sun Jiaxuan <sunjiaxuan@hotmail.com>
License: MIT License
Project-URL: Homepage, https://github.com/TianMingNanWei/terminal-stonks
Project-URL: Documentation, https://github.com/TianMingNanWei/terminal-stonks#readme
Project-URL: Repository, https://github.com/TianMingNanWei/terminal-stonks.git
Project-URL: Bug Tracker, https://github.com/TianMingNanWei/terminal-stonks/issues
Keywords: stocks,charts,terminal,visualization,candlestick
Classifier: Development Status :: 3 - Alpha
Classifier: Environment :: Console
Classifier: Intended Audience :: Developers
Classifier: Intended Audience :: Financial and Insurance Industry
Classifier: License :: OSI Approved :: MIT License
Classifier: Operating System :: OS Independent
Classifier: Programming Language :: Python :: 3
Classifier: Programming Language :: Python :: 3.8
Classifier: Programming Language :: Python :: 3.9
Classifier: Programming Language :: Python :: 3.10
Classifier: Programming Language :: Python :: 3.11
Classifier: Programming Language :: Python :: 3.12
Classifier: Topic :: Office/Business :: Financial
Classifier: Topic :: Scientific/Engineering :: Visualization
Classifier: Topic :: Software Development :: Libraries :: Python Modules
Classifier: Topic :: Terminals
Requires-Python: >=3.8
License-File: LICENSE
Requires-Dist: pandas>=1.3.0
Requires-Dist: rich>=10.0.0
Provides-Extra: dev
Requires-Dist: pytest>=7.0.0; extra == "dev"
Requires-Dist: pytest-cov>=4.0.0; extra == "dev"
Requires-Dist: black>=22.0.0; extra == "dev"
Requires-Dist: flake8>=5.0.0; extra == "dev"
Requires-Dist: mypy>=1.0.0; extra == "dev"
Requires-Dist: build>=0.8.0; extra == "dev"
Requires-Dist: twine>=4.0.0; extra == "dev"
Dynamic: license-file
